{
  "swagger": "2.0",
  "info": {
    "title": "Carts Service",
    "version": "1.0",
    "contact": {}
  },
  "schemes": [
    "http"
  ],
  "consumes": [
    "application/json"
  ],
  "produces": [
    "application/json"
  ],
  "paths": {
    "/v1/items": {
      "post": {
        "operationId": "Create",
        "responses": {
          "200": {
            "description": "A successful response.",
            "schema": {
              "$ref": "#/definitions/v1CreateResponse"
            }
          },
          "404": {
            "description": "Returned when the resource does not exist.",
            "schema": {
              "format": "string"
            }
          }
        },
        "parameters": [
          {
            "name": "body",
            "in": "body",
            "required": true,
            "schema": {
              "$ref": "#/definitions/v1CreateRequest"
            }
          }
        ],
        "tags": [
          "CartService"
        ]
      }
    },
    "/v1/items/all": {
      "get": {
        "operationId": "List",
        "responses": {
          "200": {
            "description": "A successful response.",
            "schema": {
              "$ref": "#/definitions/v1ListResponse"
            }
          },
          "404": {
            "description": "Returned when the resource does not exist.",
            "schema": {
              "format": "string"
            }
          }
        },
        "parameters": [
          {
            "name": "api",
            "in": "query",
            "required": false,
            "type": "string"
          }
        ],
        "tags": [
          "CartService"
        ]
      }
    },
    "/v1/items/{id}": {
      "get": {
        "operationId": "Read",
        "responses": {
          "200": {
            "description": "A successful response.",
            "schema": {
              "$ref": "#/definitions/v1ReadResponse"
            }
          },
          "404": {
            "description": "Returned when the resource does not exist.",
            "schema": {
              "format": "string"
            }
          }
        },
        "parameters": [
          {
            "name": "id",
            "in": "path",
            "required": true,
            "type": "string"
          },
          {
            "name": "api",
            "in": "query",
            "required": false,
            "type": "string"
          }
        ],
        "tags": [
          "CartService"
        ]
      },
      "delete": {
        "operationId": "Delete",
        "responses": {
          "200": {
            "description": "A successful response.",
            "schema": {
              "$ref": "#/definitions/v1DeleteResponse"
            }
          },
          "404": {
            "description": "Returned when the resource does not exist.",
            "schema": {
              "format": "string"
            }
          }
        },
        "parameters": [
          {
            "name": "id",
            "in": "path",
            "required": true,
            "type": "string"
          },
          {
            "name": "api",
            "in": "query",
            "required": false,
            "type": "string"
          }
        ],
        "tags": [
          "CartService"
        ]
      }
    },
    "/v1/items/{item.id}": {
      "put": {
        "operationId": "Update",
        "responses": {
          "200": {
            "description": "A successful response.",
            "schema": {
              "$ref": "#/definitions/v1UpdateResponse"
            }
          },
          "404": {
            "description": "Returned when the resource does not exist.",
            "schema": {
              "format": "string"
            }
          }
        },
        "parameters": [
          {
            "name": "item.id",
            "in": "path",
            "required": true,
            "type": "string"
          },
          {
            "name": "body",
            "in": "body",
            "required": true,
            "schema": {
              "$ref": "#/definitions/v1UpdateRequest"
            }
          }
        ],
        "tags": [
          "CartService"
        ]
      },
      "patch": {
        "operationId": "Update2",
        "responses": {
          "200": {
            "description": "A successful response.",
            "schema": {
              "$ref": "#/definitions/v1UpdateResponse"
            }
          },
          "404": {
            "description": "Returned when the resource does not exist.",
            "schema": {
              "format": "string"
            }
          }
        },
        "parameters": [
          {
            "name": "item.id",
            "in": "path",
            "required": true,
            "type": "string"
          },
          {
            "name": "body",
            "in": "body",
            "required": true,
            "schema": {
              "$ref": "#/definitions/v1UpdateRequest"
            }
          }
        ],
        "tags": [
          "CartService"
        ]
      }
    }
  },
  "definitions": {
    "CartImage": {
      "type": "object",
      "properties": {
        "id": {
          "type": "string"
        },
        "shopifyId": {
          "type": "string",
          "format": "int64"
        },
        "src": {
          "type": "string"
        },
        "alt": {
          "type": "string"
        },
        "position": {
          "type": "string"
        },
        "created": {
          "type": "string",
          "format": "date-time"
        },
        "updated": {
          "type": "string",
          "format": "date-time"
        }
      }
    },
    "CartVariant": {
      "type": "object",
      "properties": {
        "id": {
          "type": "string"
        },
        "shopifyId": {
          "type": "string",
          "format": "int64"
        },
        "title": {
          "type": "string"
        },
        "sku": {
          "type": "string"
        },
        "position": {
          "type": "string"
        },
        "regularPrice": {
          "type": "string"
        },
        "salesPrice": {
          "type": "string"
        },
        "inventoryQuantity": {
          "type": "string"
        },
        "weight": {
          "type": "string"
        },
        "created": {
          "type": "string",
          "format": "date-time"
        },
        "updated": {
          "type": "string",
          "format": "date-time"
        }
      }
    },
    "v1Collection": {
      "type": "object",
      "properties": {
        "id": {
          "type": "string"
        },
        "shopifyId": {
          "type": "string"
        },
        "title": {
          "type": "string"
        },
        "description": {
          "type": "string"
        },
        "image": {
          "type": "string"
        },
        "created": {
          "type": "string",
          "format": "date-time"
        },
        "updated": {
          "type": "string",
          "format": "date-time"
        }
      }
    },
    "v1CreateRequest": {
      "type": "object",
      "properties": {
        "api": {
          "type": "string"
        },
        "item": {
          "$ref": "#/definitions/v1Cart"
        }
      }
    },
    "v1CreateResponse": {
      "type": "object",
      "properties": {
        "api": {
          "type": "string"
        },
        "id": {
          "type": "string"
        }
      }
    },
    "v1DeleteResponse": {
      "type": "object",
      "properties": {
        "api": {
          "type": "string"
        },
        "deleted": {
          "type": "string",
          "format": "int64"
        }
      }
    },
    "v1ListResponse": {
      "type": "object",
      "properties": {
        "api": {
          "type": "string"
        },
        "data": {
          "type": "array",
          "items": {
            "$ref": "#/definitions/v1Cart"
          }
        }
      }
    },
    "v1Cart": {
      "type": "object",
      "properties": {
        "id": {
          "type": "string"
        },
        "shopifyId": {
          "type": "string",
          "format": "int64"
        },
        "title": {
          "type": "string"
        },
        "description": {
          "type": "string"
        },
        "images": {
          "type": "array",
          "items": {
            "$ref": "#/definitions/CartImage"
          }
        },
        "vendor": {
          "type": "string"
        },
        "itemType": {
          "type": "string"
        },
        "collections": {
          "type": "array",
          "items": {
            "$ref": "#/definitions/v1Collection"
          }
        },
        "tags": {
          "type": "string"
        },
        "variants": {
          "type": "array",
          "items": {
            "$ref": "#/definitions/CartVariant"
          }
        },
        "created": {
          "type": "string",
          "format": "date-time"
        },
        "updated": {
          "type": "string",
          "format": "date-time"
        }
      }
    },
    "v1ReadResponse": {
      "type": "object",
      "properties": {
        "api": {
          "type": "string"
        },
        "item": {
          "$ref": "#/definitions/v1Cart"
        }
      }
    },
    "v1UpdateRequest": {
      "type": "object",
      "properties": {
        "api": {
          "type": "string"
        },
        "item": {
          "$ref": "#/definitions/v1Cart"
        }
      }
    },
    "v1UpdateResponse": {
      "type": "object",
      "properties": {
        "api": {
          "type": "string"
        },
        "updated": {
          "type": "string",
          "format": "int64"
        }
      }
    }
  }
}
